MANIFEST.in
README.md
requirements.txt
setup.cfg
setup.py
ratio_dumper/__init__.py
ratio_dumper/cli.py
ratio_dumper/driver.py
ratio_dumper/models.py
ratio_dumper/utilities.py
ratio_dumper.egg-info/PKG-INFO
ratio_dumper.egg-info/SOURCES.txt
ratio_dumper.egg-info/dependency_links.txt
ratio_dumper.egg-info/entry_points.txt
ratio_dumper.egg-info/requires.txt
ratio_dumper.egg-info/top_level.txt
tests/__init__.py
tests/test_converter.py
tests/test_decoder.py
tests/test_driver.py
tests/test_models.py
tests/utilities.py
tests/data/dive_1.json
tests/data/dive_4.json
tests/data/sample.xml