Metadata-Version: 2.1
Name: ratio-dumper
Version: 0.0.1
Summary: Ratio iX5M Log Dumper
Home-page: https://github.com/DiveWithDamian/ratio-dumper
Author: Damian Zaremba
Author-email: oss@divewithdamian.eu
License: MIT
Keywords: ratio ix5m
Platform: any
Classifier: Programming Language :: Python :: 3
Classifier: Operating System :: OS Independent
Requires-Python: >=3.9
